pygrep/__init__.py
pygrep/__main__.py
pygrep-0.3.2.dist-info/licenses/LICENSE.txt
pygrep-0.3.2.dist-info/METADATA
pygrep-0.3.2.dist-info/WHEEL
pygrep-0.3.2.dist-info/entry_points.txt
pygrep-0.3.2.dist-info/top_level.txt
pygrep-0.3.2.dist-info/RECORD
