Metadata-Version: 2.4
Name: pygrep
Version: 0.3.2
Summary: Find python identifiers
Author-email: Axel Hecht <axel@pike.org>
License: MPL-2.0
Project-URL: source, https://github.com/Pike/pygrep
Classifier: Intended Audience :: Developers
Classifier: License :: OSI Approved :: Mozilla Public License 2.0 (MPL 2.0)
Classifier: Operating System :: OS Independent
Classifier: Programming Language :: Python :: 3
License-File: LICENSE.txt
Provides-Extra: dev
Requires-Dist: pytest; extra == "dev"
Dynamic: license-file
